{"v":5,"entries":{"configure-your-project--docs":{"id":"configure-your-project--docs","title":"Configure your project","name":"Docs","importPath":"./src/stories/Configure.mdx","storiesImports":[],"type":"docs","tags":["dev","test","unattached-mdx"]},"example-button--docs":{"id":"example-button--docs","title":"Example/Button","name":"Docs","importPath":"./src/stories/Button.stories.ts","type":"docs","tags":["dev","test","autodocs"],"storiesImports":[]},"example-button--primary":{"type":"story","id":"example-button--primary","name":"Primary","title":"Example/Button","importPath":"./src/stories/Button.stories.ts","componentPath":"./src/stories/Button.tsx","tags":["dev","test","autodocs"]},"example-button--secondary":{"type":"story","id":"example-button--secondary","name":"Secondary","title":"Example/Button","importPath":"./src/stories/Button.stories.ts","componentPath":"./src/stories/Button.tsx","tags":["dev","test","autodocs"]},"example-button--large":{"type":"story","id":"example-button--large","name":"Large","title":"Example/Button","importPath":"./src/stories/Button.stories.ts","componentPath":"./src/stories/Button.tsx","tags":["dev","test","autodocs"]},"example-button--small":{"type":"story","id":"example-button--small","name":"Small","title":"Example/Button","importPath":"./src/stories/Button.stories.ts","componentPath":"./src/stories/Button.tsx","tags":["dev","test","autodocs"]},"example-header--docs":{"id":"example-header--docs","title":"Example/Header","name":"Docs","importPath":"./src/stories/Header.stories.ts","type":"docs","tags":["dev","test","autodocs"],"storiesImports":[]},"example-header--logged-in":{"type":"story","id":"example-header--logged-in","name":"Logged In","title":"Example/Header","importPath":"./src/stories/Header.stories.ts","componentPath":"./src/stories/Header.tsx","tags":["dev","test","autodocs"]},"example-header--logged-out":{"type":"story","id":"example-header--logged-out","name":"Logged Out","title":"Example/Header","importPath":"./src/stories/Header.stories.ts","componentPath":"./src/stories/Header.tsx","tags":["dev","test","autodocs"]},"example-image--splash":{"type":"story","id":"example-image--splash","name":"Splash","title":"Example/Image","importPath":"./src/stories/Image.stories.ts","componentPath":"./src/stories/Image.tsx","tags":["dev","test"]},"example-image--messages-ignore-title-and-time":{"type":"story","id":"example-image--messages-ignore-title-and-time","name":"Messages Ignore Title And Time","title":"Example/Image","importPath":"./src/stories/Image.stories.ts","componentPath":"./src/stories/Image.tsx","tags":["dev","test"]},"example-image--messages-ignore-complete-message":{"type":"story","id":"example-image--messages-ignore-complete-message","name":"Messages Ignore Complete Message","title":"Example/Image","importPath":"./src/stories/Image.stories.ts","componentPath":"./src/stories/Image.tsx","tags":["dev","test"]},"example-image--messages-ignore-only-time":{"type":"story","id":"example-image--messages-ignore-only-time","name":"Messages Ignore Only Time","title":"Example/Image","importPath":"./src/stories/Image.stories.ts","componentPath":"./src/stories/Image.tsx","tags":["dev","test"]},"example-page--logged-out":{"type":"story","id":"example-page--logged-out","name":"Logged Out","title":"Example/Page","importPath":"./src/stories/Page.stories.ts","componentPath":"./src/stories/Page.tsx","tags":["dev","test"]},"example-page--logged-in":{"type":"story","id":"example-page--logged-in","name":"Logged In","title":"Example/Page","importPath":"./src/stories/Page.stories.ts","componentPath":"./src/stories/Page.tsx","tags":["dev","test","play-fn"]},"stories-image-dynamic--splash":{"type":"story","id":"stories-image-dynamic--splash","name":"Splash","title":"stories/Image.dynamic","importPath":"./src/stories/Image.dynamic.ts","componentPath":"./src/stories/Image.tsx","tags":["dev","test"]},"stories-image-dynamic--messages-ignore-title-and-time":{"type":"story","id":"stories-image-dynamic--messages-ignore-title-and-time","name":"Messages Ignore Title And Time","title":"stories/Image.dynamic","importPath":"./src/stories/Image.dynamic.ts","componentPath":"./src/stories/Image.tsx","tags":["dev","test"]},"stories-image-dynamic--messages-ignore-complete-message":{"type":"story","id":"stories-image-dynamic--messages-ignore-complete-message","name":"Messages Ignore Complete Message","title":"stories/Image.dynamic","importPath":"./src/stories/Image.dynamic.ts","componentPath":"./src/stories/Image.tsx","tags":["dev","test"]},"stories-image-dynamic--messages-ignore-only-time":{"type":"story","id":"stories-image-dynamic--messages-ignore-only-time","name":"Messages Ignore Only Time","title":"stories/Image.dynamic","importPath":"./src/stories/Image.dynamic.ts","componentPath":"./src/stories/Image.tsx","tags":["dev","test"]}}}
